nb2an/__init__.py
nb2an/dotnest.py
nb2an/netbox.py
nb2an/plugins/__init__.py
nb2an/plugins/update_ansible.py
nb2an/tools/__init__.py
nb2an/tools/dump.py
nb2an/tools/getdevice.py
nb2an/tools/getdevices.py
nb2an/tools/getnetwork.py
nb2an/tools/getoutlets.py
nb2an/tools/getparameters.py
nb2an/tools/getracks.py
nb2an/tools/update_ansible.py
nb2an-0.9.11.dist-info/METADATA
nb2an-0.9.11.dist-info/WHEEL
nb2an-0.9.11.dist-info/entry_points.txt
nb2an-0.9.11.dist-info/top_level.txt
nb2an-0.9.11.dist-info/RECORD
