Metadata-Version: 2.1
Name: nb2an
Version: 0.9.11
Summary: A set of python scripts to compare or update NetBox and Ansible
Home-page: https://github.com/hardaker/nb2an
Author: Wes Hardaker
Author-email: opensource@hardakers.net
Classifier: Programming Language :: Python :: 3
Classifier: Operating System :: OS Independent
Requires-Python: >=3.6
Requires-Dist: rich
Requires-Dist: ansible
Requires-Dist: ruamel.yaml
Requires-Dist: requests
Requires-Dist: pyaml
